{
  "type": "File",
  "start": 0,
  "end": 748,
  "loc": {
    "start": {
      "line": 1,
      "column": 0
    },
    "end": {
      "line": 31,
      "column": 0
    }
  },
  "program": {
    "type": "Program",
    "start": 0,
    "end": 748,
    "loc": {
      "start": {
        "line": 1,
        "column": 0
      },
      "end": {
        "line": 31,
        "column": 0
      }
    },
    "sourceType": "module",
    "body": [
      {
        "type": "ImportDeclaration",
        "start": 0,
        "end": 38,
        "loc": {
          "start": {
            "line": 1,
            "column": 0
          },
          "end": {
            "line": 1,
            "column": 38
          }
        },
        "specifiers": [
          {
            "type": "ImportDefaultSpecifier",
            "start": 7,
            "end": 17,
            "loc": {
              "start": {
                "line": 1,
                "column": 7
              },
              "end": {
                "line": 1,
                "column": 17
              }
            },
            "local": {
              "type": "Identifier",
              "start": 7,
              "end": 17,
              "loc": {
                "start": {
                  "line": 1,
                  "column": 7
                },
                "end": {
                  "line": 1,
                  "column": 17
                },
                "identifierName": "Initialize"
              },
              "name": "Initialize"
            }
          }
        ],
        "source": {
          "type": "StringLiteral",
          "start": 23,
          "end": 37,
          "loc": {
            "start": {
              "line": 1,
              "column": 23
            },
            "end": {
              "line": 1,
              "column": 37
            }
          },
          "extra": {
            "rawValue": "./Initialize",
            "raw": "'./Initialize'"
          },
          "value": "./Initialize"
        }
      },
      {
        "type": "ImportDeclaration",
        "start": 39,
        "end": 76,
        "loc": {
          "start": {
            "line": 2,
            "column": 0
          },
          "end": {
            "line": 2,
            "column": 37
          }
        },
        "specifiers": [
          {
            "type": "ImportSpecifier",
            "start": 48,
            "end": 58,
            "loc": {
              "start": {
                "line": 2,
                "column": 9
              },
              "end": {
                "line": 2,
                "column": 19
              }
            },
            "imported": {
              "type": "Identifier",
              "start": 48,
              "end": 58,
              "loc": {
                "start": {
                  "line": 2,
                  "column": 9
                },
                "end": {
                  "line": 2,
                  "column": 19
                },
                "identifierName": "createSpan"
              },
              "name": "createSpan"
            },
            "local": {
              "type": "Identifier",
              "start": 48,
              "end": 58,
              "loc": {
                "start": {
                  "line": 2,
                  "column": 9
                },
                "end": {
                  "line": 2,
                  "column": 19
                },
                "identifierName": "createSpan"
              },
              "name": "createSpan"
            }
          }
        ],
        "source": {
          "type": "StringLiteral",
          "start": 66,
          "end": 75,
          "loc": {
            "start": {
              "line": 2,
              "column": 27
            },
            "end": {
              "line": 2,
              "column": 36
            }
          },
          "extra": {
            "rawValue": "../math",
            "raw": "'../math'"
          },
          "value": "../math"
        }
      },
      {
        "type": "ExportDefaultDeclaration",
        "start": 78,
        "end": 747,
        "loc": {
          "start": {
            "line": 4,
            "column": 0
          },
          "end": {
            "line": 30,
            "column": 1
          }
        },
        "declaration": {
          "type": "ClassDeclaration",
          "start": 93,
          "end": 747,
          "loc": {
            "start": {
              "line": 4,
              "column": 15
            },
            "end": {
              "line": 30,
              "column": 1
            }
          },
          "id": {
            "type": "Identifier",
            "start": 99,
            "end": 105,
            "loc": {
              "start": {
                "line": 4,
                "column": 21
              },
              "end": {
                "line": 4,
                "column": 27
              },
              "identifierName": "Radius"
            },
            "name": "Radius"
          },
          "superClass": {
            "type": "Identifier",
            "start": 114,
            "end": 124,
            "loc": {
              "start": {
                "line": 4,
                "column": 36
              },
              "end": {
                "line": 4,
                "column": 46
              },
              "identifierName": "Initialize"
            },
            "name": "Initialize"
          },
          "body": {
            "type": "ClassBody",
            "start": 125,
            "end": 747,
            "loc": {
              "start": {
                "line": 4,
                "column": 47
              },
              "end": {
                "line": 30,
                "column": 1
              }
            },
            "body": [
              {
                "type": "ClassMethod",
                "start": 476,
                "end": 554,
                "loc": {
                  "start": {
                    "line": 17,
                    "column": 2
                  },
                  "end": {
                    "line": 20,
                    "column": 3
                  }
                },
                "static": false,
                "computed": false,
                "key": {
                  "type": "Identifier",
                  "start": 476,
                  "end": 487,
                  "loc": {
                    "start": {
                      "line": 17,
                      "column": 2
                    },
                    "end": {
                      "line": 17,
                      "column": 13
                    },
                    "identifierName": "constructor"
                  },
                  "name": "constructor",
                  "leadingComments": null
                },
                "kind": "constructor",
                "id": null,
                "generator": false,
                "expression": false,
                "async": false,
                "params": [
                  {
                    "type": "Identifier",
                    "start": 488,
                    "end": 489,
                    "loc": {
                      "start": {
                        "line": 17,
                        "column": 14
                      },
                      "end": {
                        "line": 17,
                        "column": 15
                      },
                      "identifierName": "a"
                    },
                    "name": "a"
                  },
                  {
                    "type": "Identifier",
                    "start": 491,
                    "end": 492,
                    "loc": {
                      "start": {
                        "line": 17,
                        "column": 17
                      },
                      "end": {
                        "line": 17,
                        "column": 18
                      },
                      "identifierName": "b"
                    },
                    "name": "b"
                  },
                  {
                    "type": "Identifier",
                    "start": 494,
                    "end": 495,
                    "loc": {
                      "start": {
                        "line": 17,
                        "column": 20
                      },
                      "end": {
                        "line": 17,
                        "column": 21
                      },
                      "identifierName": "c"
                    },
                    "name": "c"
                  }
                ],
                "body": {
                  "type": "BlockStatement",
                  "start": 497,
                  "end": 554,
                  "loc": {
                    "start": {
                      "line": 17,
                      "column": 23
                    },
                    "end": {
                      "line": 20,
                      "column": 3
                    }
                  },
                  "body": [
                    {
                      "type": "ExpressionStatement",
                      "start": 503,
                      "end": 511,
                      "loc": {
                        "start": {
                          "line": 18,
                          "column": 4
                        },
                        "end": {
                          "line": 18,
                          "column": 12
                        }
                      },
                      "expression": {
                        "type": "CallExpression",
                        "start": 503,
                        "end": 510,
                        "loc": {
                          "start": {
                            "line": 18,
                            "column": 4
                          },
                          "end": {
                            "line": 18,
                            "column": 11
                          }
                        },
                        "callee": {
                          "type": "Super",
                          "start": 503,
                          "end": 508,
                          "loc": {
                            "start": {
                              "line": 18,
                              "column": 4
                            },
                            "end": {
                              "line": 18,
                              "column": 9
                            }
                          }
                        },
                        "arguments": []
                      }
                    },
                    {
                      "type": "ExpressionStatement",
                      "start": 516,
                      "end": 550,
                      "loc": {
                        "start": {
                          "line": 19,
                          "column": 4
                        },
                        "end": {
                          "line": 19,
                          "column": 38
                        }
                      },
                      "expression": {
                        "type": "AssignmentExpression",
                        "start": 516,
                        "end": 549,
                        "loc": {
                          "start": {
                            "line": 19,
                            "column": 4
                          },
                          "end": {
                            "line": 19,
                            "column": 37
                          }
                        },
                        "operator": "=",
                        "left": {
                          "type": "MemberExpression",
                          "start": 516,
                          "end": 527,
                          "loc": {
                            "start": {
                              "line": 19,
                              "column": 4
                            },
                            "end": {
                              "line": 19,
                              "column": 15
                            }
                          },
                          "object": {
                            "type": "ThisExpression",
                            "start": 516,
                            "end": 520,
                            "loc": {
                              "start": {
                                "line": 19,
                                "column": 4
                              },
                              "end": {
                                "line": 19,
                                "column": 8
                              }
                            }
                          },
                          "property": {
                            "type": "Identifier",
                            "start": 521,
                            "end": 527,
                            "loc": {
                              "start": {
                                "line": 19,
                                "column": 9
                              },
                              "end": {
                                "line": 19,
                                "column": 15
                              },
                              "identifierName": "radius"
                            },
                            "name": "radius"
                          },
                          "computed": false
                        },
                        "right": {
                          "type": "CallExpression",
                          "start": 530,
                          "end": 549,
                          "loc": {
                            "start": {
                              "line": 19,
                              "column": 18
                            },
                            "end": {
                              "line": 19,
                              "column": 37
                            }
                          },
                          "callee": {
                            "type": "Identifier",
                            "start": 530,
                            "end": 540,
                            "loc": {
                              "start": {
                                "line": 19,
                                "column": 18
                              },
                              "end": {
                                "line": 19,
                                "column": 28
                              },
                              "identifierName": "createSpan"
                            },
                            "name": "createSpan"
                          },
                          "arguments": [
                            {
                              "type": "Identifier",
                              "start": 541,
                              "end": 542,
                              "loc": {
                                "start": {
                                  "line": 19,
                                  "column": 29
                                },
                                "end": {
                                  "line": 19,
                                  "column": 30
                                },
                                "identifierName": "a"
                              },
                              "name": "a"
                            },
                            {
                              "type": "Identifier",
                              "start": 544,
                              "end": 545,
                              "loc": {
                                "start": {
                                  "line": 19,
                                  "column": 32
                                },
                                "end": {
                                  "line": 19,
                                  "column": 33
                                },
                                "identifierName": "b"
                              },
                              "name": "b"
                            },
                            {
                              "type": "Identifier",
                              "start": 547,
                              "end": 548,
                              "loc": {
                                "start": {
                                  "line": 19,
                                  "column": 35
                                },
                                "end": {
                                  "line": 19,
                                  "column": 36
                                },
                                "identifierName": "c"
                              },
                              "name": "c"
                            }
                          ]
                        }
                      }
                    }
                  ],
                  "directives": []
                },
                "leadingComments": [
                  {
                    "type": "CommentBlock",
                    "value": "*\n   * Radius is init particle's Radius\n   * @param {Number} a - the Radius's start point\n   * @param {Number} b - the Radius's end point\n   * @param {String} c - span's center\n   * @example\n   * var Radius = new Proton.Radius(3,5);\n   * or\n   * var Radius = new Proton.Radius(3,1,\"center\");\n   * @extends {Initialize}\n   * @constructor\n   ",
                    "start": 129,
                    "end": 473,
                    "loc": {
                      "start": {
                        "line": 5,
                        "column": 2
                      },
                      "end": {
                        "line": 16,
                        "column": 5
                      }
                    }
                  }
                ]
              },
              {
                "type": "ClassMethod",
                "start": 558,
                "end": 617,
                "loc": {
                  "start": {
                    "line": 22,
                    "column": 2
                  },
                  "end": {
                    "line": 24,
                    "column": 3
                  }
                },
                "static": false,
                "computed": false,
                "key": {
                  "type": "Identifier",
                  "start": 558,
                  "end": 563,
                  "loc": {
                    "start": {
                      "line": 22,
                      "column": 2
                    },
                    "end": {
                      "line": 22,
                      "column": 7
                    },
                    "identifierName": "reset"
                  },
                  "name": "reset"
                },
                "kind": "method",
                "id": null,
                "generator": false,
                "expression": false,
                "async": false,
                "params": [
                  {
                    "type": "Identifier",
                    "start": 564,
                    "end": 565,
                    "loc": {
                      "start": {
                        "line": 22,
                        "column": 8
                      },
                      "end": {
                        "line": 22,
                        "column": 9
                      },
                      "identifierName": "a"
                    },
                    "name": "a"
                  },
                  {
                    "type": "Identifier",
                    "start": 567,
                    "end": 568,
                    "loc": {
                      "start": {
                        "line": 22,
                        "column": 11
                      },
                      "end": {
                        "line": 22,
                        "column": 12
                      },
                      "identifierName": "b"
                    },
                    "name": "b"
                  },
                  {
                    "type": "Identifier",
                    "start": 570,
                    "end": 571,
                    "loc": {
                      "start": {
                        "line": 22,
                        "column": 14
                      },
                      "end": {
                        "line": 22,
                        "column": 15
                      },
                      "identifierName": "c"
                    },
                    "name": "c"
                  }
                ],
                "body": {
                  "type": "BlockStatement",
                  "start": 573,
                  "end": 617,
                  "loc": {
                    "start": {
                      "line": 22,
                      "column": 17
                    },
                    "end": {
                      "line": 24,
                      "column": 3
                    }
                  },
                  "body": [
                    {
                      "type": "ExpressionStatement",
                      "start": 579,
                      "end": 613,
                      "loc": {
                        "start": {
                          "line": 23,
                          "column": 4
                        },
                        "end": {
                          "line": 23,
                          "column": 38
                        }
                      },
                      "expression": {
                        "type": "AssignmentExpression",
                        "start": 579,
                        "end": 612,
                        "loc": {
                          "start": {
                            "line": 23,
                            "column": 4
                          },
                          "end": {
                            "line": 23,
                            "column": 37
                          }
                        },
                        "operator": "=",
                        "left": {
                          "type": "MemberExpression",
                          "start": 579,
                          "end": 590,
                          "loc": {
                            "start": {
                              "line": 23,
                              "column": 4
                            },
                            "end": {
                              "line": 23,
                              "column": 15
                            }
                          },
                          "object": {
                            "type": "ThisExpression",
                            "start": 579,
                            "end": 583,
                            "loc": {
                              "start": {
                                "line": 23,
                                "column": 4
                              },
                              "end": {
                                "line": 23,
                                "column": 8
                              }
                            }
                          },
                          "property": {
                            "type": "Identifier",
                            "start": 584,
                            "end": 590,
                            "loc": {
                              "start": {
                                "line": 23,
                                "column": 9
                              },
                              "end": {
                                "line": 23,
                                "column": 15
                              },
                              "identifierName": "radius"
                            },
                            "name": "radius"
                          },
                          "computed": false
                        },
                        "right": {
                          "type": "CallExpression",
                          "start": 593,
                          "end": 612,
                          "loc": {
                            "start": {
                              "line": 23,
                              "column": 18
                            },
                            "end": {
                              "line": 23,
                              "column": 37
                            }
                          },
                          "callee": {
                            "type": "Identifier",
                            "start": 593,
                            "end": 603,
                            "loc": {
                              "start": {
                                "line": 23,
                                "column": 18
                              },
                              "end": {
                                "line": 23,
                                "column": 28
                              },
                              "identifierName": "createSpan"
                            },
                            "name": "createSpan"
                          },
                          "arguments": [
                            {
                              "type": "Identifier",
                              "start": 604,
                              "end": 605,
                              "loc": {
                                "start": {
                                  "line": 23,
                                  "column": 29
                                },
                                "end": {
                                  "line": 23,
                                  "column": 30
                                },
                                "identifierName": "a"
                              },
                              "name": "a"
                            },
                            {
                              "type": "Identifier",
                              "start": 607,
                              "end": 608,
                              "loc": {
                                "start": {
                                  "line": 23,
                                  "column": 32
                                },
                                "end": {
                                  "line": 23,
                                  "column": 33
                                },
                                "identifierName": "b"
                              },
                              "name": "b"
                            },
                            {
                              "type": "Identifier",
                              "start": 610,
                              "end": 611,
                              "loc": {
                                "start": {
                                  "line": 23,
                                  "column": 35
                                },
                                "end": {
                                  "line": 23,
                                  "column": 36
                                },
                                "identifierName": "c"
                              },
                              "name": "c"
                            }
                          ]
                        }
                      }
                    }
                  ],
                  "directives": []
                }
              },
              {
                "type": "ClassMethod",
                "start": 621,
                "end": 745,
                "loc": {
                  "start": {
                    "line": 26,
                    "column": 2
                  },
                  "end": {
                    "line": 29,
                    "column": 3
                  }
                },
                "static": false,
                "computed": false,
                "key": {
                  "type": "Identifier",
                  "start": 621,
                  "end": 631,
                  "loc": {
                    "start": {
                      "line": 26,
                      "column": 2
                    },
                    "end": {
                      "line": 26,
                      "column": 12
                    },
                    "identifierName": "initialize"
                  },
                  "name": "initialize"
                },
                "kind": "method",
                "id": null,
                "generator": false,
                "expression": false,
                "async": false,
                "params": [
                  {
                    "type": "Identifier",
                    "start": 632,
                    "end": 640,
                    "loc": {
                      "start": {
                        "line": 26,
                        "column": 13
                      },
                      "end": {
                        "line": 26,
                        "column": 21
                      },
                      "identifierName": "particle"
                    },
                    "name": "particle"
                  }
                ],
                "body": {
                  "type": "BlockStatement",
                  "start": 642,
                  "end": 745,
                  "loc": {
                    "start": {
                      "line": 26,
                      "column": 23
                    },
                    "end": {
                      "line": 29,
                      "column": 3
                    }
                  },
                  "body": [
                    {
                      "type": "ExpressionStatement",
                      "start": 648,
                      "end": 689,
                      "loc": {
                        "start": {
                          "line": 27,
                          "column": 4
                        },
                        "end": {
                          "line": 27,
                          "column": 45
                        }
                      },
                      "expression": {
                        "type": "AssignmentExpression",
                        "start": 648,
                        "end": 688,
                        "loc": {
                          "start": {
                            "line": 27,
                            "column": 4
                          },
                          "end": {
                            "line": 27,
                            "column": 44
                          }
                        },
                        "operator": "=",
                        "left": {
                          "type": "MemberExpression",
                          "start": 648,
                          "end": 663,
                          "loc": {
                            "start": {
                              "line": 27,
                              "column": 4
                            },
                            "end": {
                              "line": 27,
                              "column": 19
                            }
                          },
                          "object": {
                            "type": "Identifier",
                            "start": 648,
                            "end": 656,
                            "loc": {
                              "start": {
                                "line": 27,
                                "column": 4
                              },
                              "end": {
                                "line": 27,
                                "column": 12
                              },
                              "identifierName": "particle"
                            },
                            "name": "particle"
                          },
                          "property": {
                            "type": "Identifier",
                            "start": 657,
                            "end": 663,
                            "loc": {
                              "start": {
                                "line": 27,
                                "column": 13
                              },
                              "end": {
                                "line": 27,
                                "column": 19
                              },
                              "identifierName": "radius"
                            },
                            "name": "radius"
                          },
                          "computed": false
                        },
                        "right": {
                          "type": "CallExpression",
                          "start": 666,
                          "end": 688,
                          "loc": {
                            "start": {
                              "line": 27,
                              "column": 22
                            },
                            "end": {
                              "line": 27,
                              "column": 44
                            }
                          },
                          "callee": {
                            "type": "MemberExpression",
                            "start": 666,
                            "end": 686,
                            "loc": {
                              "start": {
                                "line": 27,
                                "column": 22
                              },
                              "end": {
                                "line": 27,
                                "column": 42
                              }
                            },
                            "object": {
                              "type": "MemberExpression",
                              "start": 666,
                              "end": 677,
                              "loc": {
                                "start": {
                                  "line": 27,
                                  "column": 22
                                },
                                "end": {
                                  "line": 27,
                                  "column": 33
                                }
                              },
                              "object": {
                                "type": "ThisExpression",
                                "start": 666,
                                "end": 670,
                                "loc": {
                                  "start": {
                                    "line": 27,
                                    "column": 22
                                  },
                                  "end": {
                                    "line": 27,
                                    "column": 26
                                  }
                                }
                              },
                              "property": {
                                "type": "Identifier",
                                "start": 671,
                                "end": 677,
                                "loc": {
                                  "start": {
                                    "line": 27,
                                    "column": 27
                                  },
                                  "end": {
                                    "line": 27,
                                    "column": 33
                                  },
                                  "identifierName": "radius"
                                },
                                "name": "radius"
                              },
                              "computed": false
                            },
                            "property": {
                              "type": "Identifier",
                              "start": 678,
                              "end": 686,
                              "loc": {
                                "start": {
                                  "line": 27,
                                  "column": 34
                                },
                                "end": {
                                  "line": 27,
                                  "column": 42
                                },
                                "identifierName": "getValue"
                              },
                              "name": "getValue"
                            },
                            "computed": false
                          },
                          "arguments": []
                        }
                      }
                    },
                    {
                      "type": "ExpressionStatement",
                      "start": 694,
                      "end": 741,
                      "loc": {
                        "start": {
                          "line": 28,
                          "column": 4
                        },
                        "end": {
                          "line": 28,
                          "column": 51
                        }
                      },
                      "expression": {
                        "type": "AssignmentExpression",
                        "start": 694,
                        "end": 740,
                        "loc": {
                          "start": {
                            "line": 28,
                            "column": 4
                          },
                          "end": {
                            "line": 28,
                            "column": 50
                          }
                        },
                        "operator": "=",
                        "left": {
                          "type": "MemberExpression",
                          "start": 694,
                          "end": 722,
                          "loc": {
                            "start": {
                              "line": 28,
                              "column": 4
                            },
                            "end": {
                              "line": 28,
                              "column": 32
                            }
                          },
                          "object": {
                            "type": "MemberExpression",
                            "start": 694,
                            "end": 712,
                            "loc": {
                              "start": {
                                "line": 28,
                                "column": 4
                              },
                              "end": {
                                "line": 28,
                                "column": 22
                              }
                            },
                            "object": {
                              "type": "Identifier",
                              "start": 694,
                              "end": 702,
                              "loc": {
                                "start": {
                                  "line": 28,
                                  "column": 4
                                },
                                "end": {
                                  "line": 28,
                                  "column": 12
                                },
                                "identifierName": "particle"
                              },
                              "name": "particle"
                            },
                            "property": {
                              "type": "Identifier",
                              "start": 703,
                              "end": 712,
                              "loc": {
                                "start": {
                                  "line": 28,
                                  "column": 13
                                },
                                "end": {
                                  "line": 28,
                                  "column": 22
                                },
                                "identifierName": "transform"
                              },
                              "name": "transform"
                            },
                            "computed": false
                          },
                          "property": {
                            "type": "Identifier",
                            "start": 713,
                            "end": 722,
                            "loc": {
                              "start": {
                                "line": 28,
                                "column": 23
                              },
                              "end": {
                                "line": 28,
                                "column": 32
                              },
                              "identifierName": "oldRadius"
                            },
                            "name": "oldRadius"
                          },
                          "computed": false
                        },
                        "right": {
                          "type": "MemberExpression",
                          "start": 725,
                          "end": 740,
                          "loc": {
                            "start": {
                              "line": 28,
                              "column": 35
                            },
                            "end": {
                              "line": 28,
                              "column": 50
                            }
                          },
                          "object": {
                            "type": "Identifier",
                            "start": 725,
                            "end": 733,
                            "loc": {
                              "start": {
                                "line": 28,
                                "column": 35
                              },
                              "end": {
                                "line": 28,
                                "column": 43
                              },
                              "identifierName": "particle"
                            },
                            "name": "particle"
                          },
                          "property": {
                            "type": "Identifier",
                            "start": 734,
                            "end": 740,
                            "loc": {
                              "start": {
                                "line": 28,
                                "column": 44
                              },
                              "end": {
                                "line": 28,
                                "column": 50
                              },
                              "identifierName": "radius"
                            },
                            "name": "radius"
                          },
                          "computed": false
                        }
                      }
                    }
                  ],
                  "directives": []
                }
              }
            ]
          },
          "leadingComments": [],
          "trailingComments": []
        }
      }
    ],
    "directives": []
  },
  "comments": [
    {
      "type": "CommentBlock",
      "value": "*\n   * Radius is init particle's Radius\n   * @param {Number} a - the Radius's start point\n   * @param {Number} b - the Radius's end point\n   * @param {String} c - span's center\n   * @example\n   * var Radius = new Proton.Radius(3,5);\n   * or\n   * var Radius = new Proton.Radius(3,1,\"center\");\n   * @extends {Initialize}\n   * @constructor\n   ",
      "start": 129,
      "end": 473,
      "loc": {
        "start": {
          "line": 5,
          "column": 2
        },
        "end": {
          "line": 16,
          "column": 5
        }
      }
    }
  ],
  "tokens": [
    {
      "type": {
        "label": "import",
        "keyword": "import",
        "beforeExpr": false,
        "startsExpr": true,
        "rightAssociative": false,
        "isLoop": false,
        "isAssign": false,
        "prefix": false,
        "postfix": false,
        "binop": null,
        "updateContext": null
      },
      "value": "import",
      "start": 0,
      "end": 6,
      "loc": {
        "start": {
          "line": 1,
          "column": 0
        },
        "end": {
          "line": 1,
          "column": 6
        }
      }
    },
    {
      "type": {
        "label": "name",
        "beforeExpr": false,
        "startsExpr": true,
        "rightAssociative": false,
        "isLoop": false,
        "isAssign": false,
        "prefix": false,
        "postfix": false,
        "binop": null
      },
      "value": "Initialize",
      "start": 7,
      "end": 17,
      "loc": {
        "start": {
          "line": 1,
          "column": 7
        },
        "end": {
          "line": 1,
          "column": 17
        }
      }
    },
    {
      "type": {
        "label": "name",
        "beforeExpr": false,
        "startsExpr": true,
        "rightAssociative": false,
        "isLoop": false,
        "isAssign": false,
        "prefix": false,
        "postfix": false,
        "binop": null
      },
      "value": "from",
      "start": 18,
      "end": 22,
      "loc": {
        "start": {
          "line": 1,
          "column": 18
        },
        "end": {
          "line": 1,
          "column": 22
        }
      }
    },
    {
      "type": {
        "label": "string",
        "beforeExpr": false,
        "startsExpr": true,
        "rightAssociative": false,
        "isLoop": false,
        "isAssign": false,
        "prefix": false,
        "postfix": false,
        "binop": null,
        "updateContext": null
      },
      "value": "./Initialize",
      "start": 23,
      "end": 37,
      "loc": {
        "start": {
          "line": 1,
          "column": 23
        },
        "end": {
          "line": 1,
          "column": 37
        }
      }
    },
    {
      "type": {
        "label": ";",
        "beforeExpr": true,
        "startsExpr": false,
        "rightAssociative": false,
        "isLoop": false,
        "isAssign": false,
        "prefix": false,
        "postfix": false,
        "binop": null,
        "updateContext": null
      },
      "start": 37,
      "end": 38,
      "loc": {
        "start": {
          "line": 1,
          "column": 37
        },
        "end": {
          "line": 1,
          "column": 38
        }
      }
    },
    {
      "type": {
        "label": "import",
        "keyword": "import",
        "beforeExpr": false,
        "startsExpr": true,
        "rightAssociative": false,
        "isLoop": false,
        "isAssign": false,
        "prefix": false,
        "postfix": false,
        "binop": null,
        "updateContext": null
      },
      "value": "import",
      "start": 39,
      "end": 45,
      "loc": {
        "start": {
          "line": 2,
          "column": 0
        },
        "end": {
          "line": 2,
          "column": 6
        }
      }
    },
    {
      "type": {
        "label": "{",
        "beforeExpr": true,
        "startsExpr": true,
        "rightAssociative": false,
        "isLoop": false,
        "isAssign": false,
        "prefix": false,
        "postfix": false,
        "binop": null
      },
      "start": 46,
      "end": 47,
      "loc": {
        "start": {
          "line": 2,
          "column": 7
        },
        "end": {
          "line": 2,
          "column": 8
        }
      }
    },
    {
      "type": {
        "label": "name",
        "beforeExpr": false,
        "startsExpr": true,
        "rightAssociative": false,
        "isLoop": false,
        "isAssign": false,
        "prefix": false,
        "postfix": false,
        "binop": null
      },
      "value": "createSpan",
      "start": 48,
      "end": 58,
      "loc": {
        "start": {
          "line": 2,
          "column": 9
        },
        "end": {
          "line": 2,
          "column": 19
        }
      }
    },
    {
      "type": {
        "label": "}",
        "beforeExpr": false,
        "startsExpr": false,
        "rightAssociative": false,
        "isLoop": false,
        "isAssign": false,
        "prefix": false,
        "postfix": false,
        "binop": null
      },
      "start": 59,
      "end": 60,
      "loc": {
        "start": {
          "line": 2,
          "column": 20
        },
        "end": {
          "line": 2,
          "column": 21
        }
      }
    },
    {
      "type": {
        "label": "name",
        "beforeExpr": false,
        "startsExpr": true,
        "rightAssociative": false,
        "isLoop": false,
        "isAssign": false,
        "prefix": false,
        "postfix": false,
        "binop": null
      },
      "value": "from",
      "start": 61,
      "end": 65,
      "loc": {
        "start": {
          "line": 2,
          "column": 22
        },
        "end": {
          "line": 2,
          "column": 26
        }
      }
    },
    {
      "type": {
        "label": "string",
        "beforeExpr": false,
        "startsExpr": true,
        "rightAssociative": false,
        "isLoop": false,
        "isAssign": false,
        "prefix": false,
        "postfix": false,
        "binop": null,
        "updateContext": null
      },
      "value": "../math",
      "start": 66,
      "end": 75,
      "loc": {
        "start": {
          "line": 2,
          "column": 27
        },
        "end": {
          "line": 2,
          "column": 36
        }
      }
    },
    {
      "type": {
        "label": ";",
        "beforeExpr": true,
        "startsExpr": false,
        "rightAssociative": false,
        "isLoop": false,
        "isAssign": false,
        "prefix": false,
        "postfix": false,
        "binop": null,
        "updateContext": null
      },
      "start": 75,
      "end": 76,
      "loc": {
        "start": {
          "line": 2,
          "column": 36
        },
        "end": {
          "line": 2,
          "column": 37
        }
      }
    },
    {
      "type": {
        "label": "export",
        "keyword": "export",
        "beforeExpr": false,
        "startsExpr": false,
        "rightAssociative": false,
        "isLoop": false,
        "isAssign": false,
        "prefix": false,
        "postfix": false,
        "binop": null,
        "updateContext": null
      },
      "value": "export",
      "start": 78,
      "end": 84,
      "loc": {
        "start": {
          "line": 4,
          "column": 0
        },
        "end": {
          "line": 4,
          "column": 6
        }
      }
    },
    {
      "type": {
        "label": "default",
        "keyword": "default",
        "beforeExpr": true,
        "startsExpr": false,
        "rightAssociative": false,
        "isLoop": false,
        "isAssign": false,
        "prefix": false,
        "postfix": false,
        "binop": null,
        "updateContext": null
      },
      "value": "default",
      "start": 85,
      "end": 92,
      "loc": {
        "start": {
          "line": 4,
          "column": 7
        },
        "end": {
          "line": 4,
          "column": 14
        }
      }
    },
    {
      "type": {
        "label": "class",
        "keyword": "class",
        "beforeExpr": false,
        "startsExpr": false,
        "rightAssociative": false,
        "isLoop": false,
        "isAssign": false,
        "prefix": false,
        "postfix": false,
        "binop": null,
        "updateContext": null
      },
      "value": "class",
      "start": 93,
      "end": 98,
      "loc": {
        "start": {
          "line": 4,
          "column": 15
        },
        "end": {
          "line": 4,
          "column": 20
        }
      }
    },
    {
      "type": {
        "label": "name",
        "beforeExpr": false,
        "startsExpr": true,
        "rightAssociative": false,
        "isLoop": false,
        "isAssign": false,
        "prefix": false,
        "postfix": false,
        "binop": null
      },
      "value": "Radius",
      "start": 99,
      "end": 105,
      "loc": {
        "start": {
          "line": 4,
          "column": 21
        },
        "end": {
          "line": 4,
          "column": 27
        }
      }
    },
    {
      "type": {
        "label": "extends",
        "keyword": "extends",
        "beforeExpr": true,
        "startsExpr": false,
        "rightAssociative": false,
        "isLoop": false,
        "isAssign": false,
        "prefix": false,
        "postfix": false,
        "binop": null,
        "updateContext": null
      },
      "value": "extends",
      "start": 106,
      "end": 113,
      "loc": {
        "start": {
          "line": 4,
          "column": 28
        },
        "end": {
          "line": 4,
          "column": 35
        }
      }
    },
    {
      "type": {
        "label": "name",
        "beforeExpr": false,
        "startsExpr": true,
        "rightAssociative": false,
        "isLoop": false,
        "isAssign": false,
        "prefix": false,
        "postfix": false,
        "binop": null
      },
      "value": "Initialize",
      "start": 114,
      "end": 124,
      "loc": {
        "start": {
          "line": 4,
          "column": 36
        },
        "end": {
          "line": 4,
          "column": 46
        }
      }
    },
    {
      "type": {
        "label": "{",
        "beforeExpr": true,
        "startsExpr": true,
        "rightAssociative": false,
        "isLoop": false,
        "isAssign": false,
        "prefix": false,
        "postfix": false,
        "binop": null
      },
      "start": 125,
      "end": 126,
      "loc": {
        "start": {
          "line": 4,
          "column": 47
        },
        "end": {
          "line": 4,
          "column": 48
        }
      }
    },
    {
      "type": "CommentBlock",
      "value": "*\n   * Radius is init particle's Radius\n   * @param {Number} a - the Radius's start point\n   * @param {Number} b - the Radius's end point\n   * @param {String} c - span's center\n   * @example\n   * var Radius = new Proton.Radius(3,5);\n   * or\n   * var Radius = new Proton.Radius(3,1,\"center\");\n   * @extends {Initialize}\n   * @constructor\n   ",
      "start": 129,
      "end": 473,
      "loc": {
        "start": {
          "line": 5,
          "column": 2
        },
        "end": {
          "line": 16,
          "column": 5
        }
      }
    },
    {
      "type": {
        "label": "name",
        "beforeExpr": false,
        "startsExpr": true,
        "rightAssociative": false,
        "isLoop": false,
        "isAssign": false,
        "prefix": false,
        "postfix": false,
        "binop": null
      },
      "value": "constructor",
      "start": 476,
      "end": 487,
      "loc": {
        "start": {
          "line": 17,
          "column": 2
        },
        "end": {
          "line": 17,
          "column": 13
        }
      }
    },
    {
      "type": {
        "label": "(",
        "beforeExpr": true,
        "startsExpr": true,
        "rightAssociative": false,
        "isLoop": false,
        "isAssign": false,
        "prefix": false,
        "postfix": false,
        "binop": null
      },
      "start": 487,
      "end": 488,
      "loc": {
        "start": {
          "line": 17,
          "column": 13
        },
        "end": {
          "line": 17,
          "column": 14
        }
      }
    },
    {
      "type": {
        "label": "name",
        "beforeExpr": false,
        "startsExpr": true,
        "rightAssociative": false,
        "isLoop": false,
        "isAssign": false,
        "prefix": false,
        "postfix": false,
        "binop": null
      },
      "value": "a",
      "start": 488,
      "end": 489,
      "loc": {
        "start": {
          "line": 17,
          "column": 14
        },
        "end": {
          "line": 17,
          "column": 15
        }
      }
    },
    {
      "type": {
        "label": ",",
        "beforeExpr": true,
        "startsExpr": false,
        "rightAssociative": false,
        "isLoop": false,
        "isAssign": false,
        "prefix": false,
        "postfix": false,
        "binop": null,
        "updateContext": null
      },
      "start": 489,
      "end": 490,
      "loc": {
        "start": {
          "line": 17,
          "column": 15
        },
        "end": {
          "line": 17,
          "column": 16
        }
      }
    },
    {
      "type": {
        "label": "name",
        "beforeExpr": false,
        "startsExpr": true,
        "rightAssociative": false,
        "isLoop": false,
        "isAssign": false,
        "prefix": false,
        "postfix": false,
        "binop": null
      },
      "value": "b",
      "start": 491,
      "end": 492,
      "loc": {
        "start": {
          "line": 17,
          "column": 17
        },
        "end": {
          "line": 17,
          "column": 18
        }
      }
    },
    {
      "type": {
        "label": ",",
        "beforeExpr": true,
        "startsExpr": false,
        "rightAssociative": false,
        "isLoop": false,
        "isAssign": false,
        "prefix": false,
        "postfix": false,
        "binop": null,
        "updateContext": null
      },
      "start": 492,
      "end": 493,
      "loc": {
        "start": {
          "line": 17,
          "column": 18
        },
        "end": {
          "line": 17,
          "column": 19
        }
      }
    },
    {
      "type": {
        "label": "name",
        "beforeExpr": false,
        "startsExpr": true,
        "rightAssociative": false,
        "isLoop": false,
        "isAssign": false,
        "prefix": false,
        "postfix": false,
        "binop": null
      },
      "value": "c",
      "start": 494,
      "end": 495,
      "loc": {
        "start": {
          "line": 17,
          "column": 20
        },
        "end": {
          "line": 17,
          "column": 21
        }
      }
    },
    {
      "type": {
        "label": ")",
        "beforeExpr": false,
        "startsExpr": false,
        "rightAssociative": false,
        "isLoop": false,
        "isAssign": false,
        "prefix": false,
        "postfix": false,
        "binop": null
      },
      "start": 495,
      "end": 496,
      "loc": {
        "start": {
          "line": 17,
          "column": 21
        },
        "end": {
          "line": 17,
          "column": 22
        }
      }
    },
    {
      "type": {
        "label": "{",
        "beforeExpr": true,
        "startsExpr": true,
        "rightAssociative": false,
        "isLoop": false,
        "isAssign": false,
        "prefix": false,
        "postfix": false,
        "binop": null
      },
      "start": 497,
      "end": 498,
      "loc": {
        "start": {
          "line": 17,
          "column": 23
        },
        "end": {
          "line": 17,
          "column": 24
        }
      }
    },
    {
      "type": {
        "label": "super",
        "keyword": "super",
        "beforeExpr": false,
        "startsExpr": true,
        "rightAssociative": false,
        "isLoop": false,
        "isAssign": false,
        "prefix": false,
        "postfix": false,
        "binop": null,
        "updateContext": null
      },
      "value": "super",
      "start": 503,
      "end": 508,
      "loc": {
        "start": {
          "line": 18,
          "column": 4
        },
        "end": {
          "line": 18,
          "column": 9
        }
      }
    },
    {
      "type": {
        "label": "(",
        "beforeExpr": true,
        "startsExpr": true,
        "rightAssociative": false,
        "isLoop": false,
        "isAssign": false,
        "prefix": false,
        "postfix": false,
        "binop": null
      },
      "start": 508,
      "end": 509,
      "loc": {
        "start": {
          "line": 18,
          "column": 9
        },
        "end": {
          "line": 18,
          "column": 10
        }
      }
    },
    {
      "type": {
        "label": ")",
        "beforeExpr": false,
        "startsExpr": false,
        "rightAssociative": false,
        "isLoop": false,
        "isAssign": false,
        "prefix": false,
        "postfix": false,
        "binop": null
      },
      "start": 509,
      "end": 510,
      "loc": {
        "start": {
          "line": 18,
          "column": 10
        },
        "end": {
          "line": 18,
          "column": 11
        }
      }
    },
    {
      "type": {
        "label": ";",
        "beforeExpr": true,
        "startsExpr": false,
        "rightAssociative": false,
        "isLoop": false,
        "isAssign": false,
        "prefix": false,
        "postfix": false,
        "binop": null,
        "updateContext": null
      },
      "start": 510,
      "end": 511,
      "loc": {
        "start": {
          "line": 18,
          "column": 11
        },
        "end": {
          "line": 18,
          "column": 12
        }
      }
    },
    {
      "type": {
        "label": "this",
        "keyword": "this",
        "beforeExpr": false,
        "startsExpr": true,
        "rightAssociative": false,
        "isLoop": false,
        "isAssign": false,
        "prefix": false,
        "postfix": false,
        "binop": null,
        "updateContext": null
      },
      "value": "this",
      "start": 516,
      "end": 520,
      "loc": {
        "start": {
          "line": 19,
          "column": 4
        },
        "end": {
          "line": 19,
          "column": 8
        }
      }
    },
    {
      "type": {
        "label": ".",
        "beforeExpr": false,
        "startsExpr": false,
        "rightAssociative": false,
        "isLoop": false,
        "isAssign": false,
        "prefix": false,
        "postfix": false,
        "binop": null,
        "updateContext": null
      },
      "start": 520,
      "end": 521,
      "loc": {
        "start": {
          "line": 19,
          "column": 8
        },
        "end": {
          "line": 19,
          "column": 9
        }
      }
    },
    {
      "type": {
        "label": "name",
        "beforeExpr": false,
        "startsExpr": true,
        "rightAssociative": false,
        "isLoop": false,
        "isAssign": false,
        "prefix": false,
        "postfix": false,
        "binop": null
      },
      "value": "radius",
      "start": 521,
      "end": 527,
      "loc": {
        "start": {
          "line": 19,
          "column": 9
        },
        "end": {
          "line": 19,
          "column": 15
        }
      }
    },
    {
      "type": {
        "label": "=",
        "beforeExpr": true,
        "startsExpr": false,
        "rightAssociative": false,
        "isLoop": false,
        "isAssign": true,
        "prefix": false,
        "postfix": false,
        "binop": null,
        "updateContext": null
      },
      "value": "=",
      "start": 528,
      "end": 529,
      "loc": {
        "start": {
          "line": 19,
          "column": 16
        },
        "end": {
          "line": 19,
          "column": 17
        }
      }
    },
    {
      "type": {
        "label": "name",
        "beforeExpr": false,
        "startsExpr": true,
        "rightAssociative": false,
        "isLoop": false,
        "isAssign": false,
        "prefix": false,
        "postfix": false,
        "binop": null
      },
      "value": "createSpan",
      "start": 530,
      "end": 540,
      "loc": {
        "start": {
          "line": 19,
          "column": 18
        },
        "end": {
          "line": 19,
          "column": 28
        }
      }
    },
    {
      "type": {
        "label": "(",
        "beforeExpr": true,
        "startsExpr": true,
        "rightAssociative": false,
        "isLoop": false,
        "isAssign": false,
        "prefix": false,
        "postfix": false,
        "binop": null
      },
      "start": 540,
      "end": 541,
      "loc": {
        "start": {
          "line": 19,
          "column": 28
        },
        "end": {
          "line": 19,
          "column": 29
        }
      }
    },
    {
      "type": {
        "label": "name",
        "beforeExpr": false,
        "startsExpr": true,
        "rightAssociative": false,
        "isLoop": false,
        "isAssign": false,
        "prefix": false,
        "postfix": false,
        "binop": null
      },
      "value": "a",
      "start": 541,
      "end": 542,
      "loc": {
        "start": {
          "line": 19,
          "column": 29
        },
        "end": {
          "line": 19,
          "column": 30
        }
      }
    },
    {
      "type": {
        "label": ",",
        "beforeExpr": true,
        "startsExpr": false,
        "rightAssociative": false,
        "isLoop": false,
        "isAssign": false,
        "prefix": false,
        "postfix": false,
        "binop": null,
        "updateContext": null
      },
      "start": 542,
      "end": 543,
      "loc": {
        "start": {
          "line": 19,
          "column": 30
        },
        "end": {
          "line": 19,
          "column": 31
        }
      }
    },
    {
      "type": {
        "label": "name",
        "beforeExpr": false,
        "startsExpr": true,
        "rightAssociative": false,
        "isLoop": false,
        "isAssign": false,
        "prefix": false,
        "postfix": false,
        "binop": null
      },
      "value": "b",
      "start": 544,
      "end": 545,
      "loc": {
        "start": {
          "line": 19,
          "column": 32
        },
        "end": {
          "line": 19,
          "column": 33
        }
      }
    },
    {
      "type": {
        "label": ",",
        "beforeExpr": true,
        "startsExpr": false,
        "rightAssociative": false,
        "isLoop": false,
        "isAssign": false,
        "prefix": false,
        "postfix": false,
        "binop": null,
        "updateContext": null
      },
      "start": 545,
      "end": 546,
      "loc": {
        "start": {
          "line": 19,
          "column": 33
        },
        "end": {
          "line": 19,
          "column": 34
        }
      }
    },
    {
      "type": {
        "label": "name",
        "beforeExpr": false,
        "startsExpr": true,
        "rightAssociative": false,
        "isLoop": false,
        "isAssign": false,
        "prefix": false,
        "postfix": false,
        "binop": null
      },
      "value": "c",
      "start": 547,
      "end": 548,
      "loc": {
        "start": {
          "line": 19,
          "column": 35
        },
        "end": {
          "line": 19,
          "column": 36
        }
      }
    },
    {
      "type": {
        "label": ")",
        "beforeExpr": false,
        "startsExpr": false,
        "rightAssociative": false,
        "isLoop": false,
        "isAssign": false,
        "prefix": false,
        "postfix": false,
        "binop": null
      },
      "start": 548,
      "end": 549,
      "loc": {
        "start": {
          "line": 19,
          "column": 36
        },
        "end": {
          "line": 19,
          "column": 37
        }
      }
    },
    {
      "type": {
        "label": ";",
        "beforeExpr": true,
        "startsExpr": false,
        "rightAssociative": false,
        "isLoop": false,
        "isAssign": false,
        "prefix": false,
        "postfix": false,
        "binop": null,
        "updateContext": null
      },
      "start": 549,
      "end": 550,
      "loc": {
        "start": {
          "line": 19,
          "column": 37
        },
        "end": {
          "line": 19,
          "column": 38
        }
      }
    },
    {
      "type": {
        "label": "}",
        "beforeExpr": false,
        "startsExpr": false,
        "rightAssociative": false,
        "isLoop": false,
        "isAssign": false,
        "prefix": false,
        "postfix": false,
        "binop": null
      },
      "start": 553,
      "end": 554,
      "loc": {
        "start": {
          "line": 20,
          "column": 2
        },
        "end": {
          "line": 20,
          "column": 3
        }
      }
    },
    {
      "type": {
        "label": "name",
        "beforeExpr": false,
        "startsExpr": true,
        "rightAssociative": false,
        "isLoop": false,
        "isAssign": false,
        "prefix": false,
        "postfix": false,
        "binop": null
      },
      "value": "reset",
      "start": 558,
      "end": 563,
      "loc": {
        "start": {
          "line": 22,
          "column": 2
        },
        "end": {
          "line": 22,
          "column": 7
        }
      }
    },
    {
      "type": {
        "label": "(",
        "beforeExpr": true,
        "startsExpr": true,
        "rightAssociative": false,
        "isLoop": false,
        "isAssign": false,
        "prefix": false,
        "postfix": false,
        "binop": null
      },
      "start": 563,
      "end": 564,
      "loc": {
        "start": {
          "line": 22,
          "column": 7
        },
        "end": {
          "line": 22,
          "column": 8
        }
      }
    },
    {
      "type": {
        "label": "name",
        "beforeExpr": false,
        "startsExpr": true,
        "rightAssociative": false,
        "isLoop": false,
        "isAssign": false,
        "prefix": false,
        "postfix": false,
        "binop": null
      },
      "value": "a",
      "start": 564,
      "end": 565,
      "loc": {
        "start": {
          "line": 22,
          "column": 8
        },
        "end": {
          "line": 22,
          "column": 9
        }
      }
    },
    {
      "type": {
        "label": ",",
        "beforeExpr": true,
        "startsExpr": false,
        "rightAssociative": false,
        "isLoop": false,
        "isAssign": false,
        "prefix": false,
        "postfix": false,
        "binop": null,
        "updateContext": null
      },
      "start": 565,
      "end": 566,
      "loc": {
        "start": {
          "line": 22,
          "column": 9
        },
        "end": {
          "line": 22,
          "column": 10
        }
      }
    },
    {
      "type": {
        "label": "name",
        "beforeExpr": false,
        "startsExpr": true,
        "rightAssociative": false,
        "isLoop": false,
        "isAssign": false,
        "prefix": false,
        "postfix": false,
        "binop": null
      },
      "value": "b",
      "start": 567,
      "end": 568,
      "loc": {
        "start": {
          "line": 22,
          "column": 11
        },
        "end": {
          "line": 22,
          "column": 12
        }
      }
    },
    {
      "type": {
        "label": ",",
        "beforeExpr": true,
        "startsExpr": false,
        "rightAssociative": false,
        "isLoop": false,
        "isAssign": false,
        "prefix": false,
        "postfix": false,
        "binop": null,
        "updateContext": null
      },
      "start": 568,
      "end": 569,
      "loc": {
        "start": {
          "line": 22,
          "column": 12
        },
        "end": {
          "line": 22,
          "column": 13
        }
      }
    },
    {
      "type": {
        "label": "name",
        "beforeExpr": false,
        "startsExpr": true,
        "rightAssociative": false,
        "isLoop": false,
        "isAssign": false,
        "prefix": false,
        "postfix": false,
        "binop": null
      },
      "value": "c",
      "start": 570,
      "end": 571,
      "loc": {
        "start": {
          "line": 22,
          "column": 14
        },
        "end": {
          "line": 22,
          "column": 15
        }
      }
    },
    {
      "type": {
        "label": ")",
        "beforeExpr": false,
        "startsExpr": false,
        "rightAssociative": false,
        "isLoop": false,
        "isAssign": false,
        "prefix": false,
        "postfix": false,
        "binop": null
      },
      "start": 571,
      "end": 572,
      "loc": {
        "start": {
          "line": 22,
          "column": 15
        },
        "end": {
          "line": 22,
          "column": 16
        }
      }
    },
    {
      "type": {
        "label": "{",
        "beforeExpr": true,
        "startsExpr": true,
        "rightAssociative": false,
        "isLoop": false,
        "isAssign": false,
        "prefix": false,
        "postfix": false,
        "binop": null
      },
      "start": 573,
      "end": 574,
      "loc": {
        "start": {
          "line": 22,
          "column": 17
        },
        "end": {
          "line": 22,
          "column": 18
        }
      }
    },
    {
      "type": {
        "label": "this",
        "keyword": "this",
        "beforeExpr": false,
        "startsExpr": true,
        "rightAssociative": false,
        "isLoop": false,
        "isAssign": false,
        "prefix": false,
        "postfix": false,
        "binop": null,
        "updateContext": null
      },
      "value": "this",
      "start": 579,
      "end": 583,
      "loc": {
        "start": {
          "line": 23,
          "column": 4
        },
        "end": {
          "line": 23,
          "column": 8
        }
      }
    },
    {
      "type": {
        "label": ".",
        "beforeExpr": false,
        "startsExpr": false,
        "rightAssociative": false,
        "isLoop": false,
        "isAssign": false,
        "prefix": false,
        "postfix": false,
        "binop": null,
        "updateContext": null
      },
      "start": 583,
      "end": 584,
      "loc": {
        "start": {
          "line": 23,
          "column": 8
        },
        "end": {
          "line": 23,
          "column": 9
        }
      }
    },
    {
      "type": {
        "label": "name",
        "beforeExpr": false,
        "startsExpr": true,
        "rightAssociative": false,
        "isLoop": false,
        "isAssign": false,
        "prefix": false,
        "postfix": false,
        "binop": null
      },
      "value": "radius",
      "start": 584,
      "end": 590,
      "loc": {
        "start": {
          "line": 23,
          "column": 9
        },
        "end": {
          "line": 23,
          "column": 15
        }
      }
    },
    {
      "type": {
        "label": "=",
        "beforeExpr": true,
        "startsExpr": false,
        "rightAssociative": false,
        "isLoop": false,
        "isAssign": true,
        "prefix": false,
        "postfix": false,
        "binop": null,
        "updateContext": null
      },
      "value": "=",
      "start": 591,
      "end": 592,
      "loc": {
        "start": {
          "line": 23,
          "column": 16
        },
        "end": {
          "line": 23,
          "column": 17
        }
      }
    },
    {
      "type": {
        "label": "name",
        "beforeExpr": false,
        "startsExpr": true,
        "rightAssociative": false,
        "isLoop": false,
        "isAssign": false,
        "prefix": false,
        "postfix": false,
        "binop": null
      },
      "value": "createSpan",
      "start": 593,
      "end": 603,
      "loc": {
        "start": {
          "line": 23,
          "column": 18
        },
        "end": {
          "line": 23,
          "column": 28
        }
      }
    },
    {
      "type": {
        "label": "(",
        "beforeExpr": true,
        "startsExpr": true,
        "rightAssociative": false,
        "isLoop": false,
        "isAssign": false,
        "prefix": false,
        "postfix": false,
        "binop": null
      },
      "start": 603,
      "end": 604,
      "loc": {
        "start": {
          "line": 23,
          "column": 28
        },
        "end": {
          "line": 23,
          "column": 29
        }
      }
    },
    {
      "type": {
        "label": "name",
        "beforeExpr": false,
        "startsExpr": true,
        "rightAssociative": false,
        "isLoop": false,
        "isAssign": false,
        "prefix": false,
        "postfix": false,
        "binop": null
      },
      "value": "a",
      "start": 604,
      "end": 605,
      "loc": {
        "start": {
          "line": 23,
          "column": 29
        },
        "end": {
          "line": 23,
          "column": 30
        }
      }
    },
    {
      "type": {
        "label": ",",
        "beforeExpr": true,
        "startsExpr": false,
        "rightAssociative": false,
        "isLoop": false,
        "isAssign": false,
        "prefix": false,
        "postfix": false,
        "binop": null,
        "updateContext": null
      },
      "start": 605,
      "end": 606,
      "loc": {
        "start": {
          "line": 23,
          "column": 30
        },
        "end": {
          "line": 23,
          "column": 31
        }
      }
    },
    {
      "type": {
        "label": "name",
        "beforeExpr": false,
        "startsExpr": true,
        "rightAssociative": false,
        "isLoop": false,
        "isAssign": false,
        "prefix": false,
        "postfix": false,
        "binop": null
      },
      "value": "b",
      "start": 607,
      "end": 608,
      "loc": {
        "start": {
          "line": 23,
          "column": 32
        },
        "end": {
          "line": 23,
          "column": 33
        }
      }
    },
    {
      "type": {
        "label": ",",
        "beforeExpr": true,
        "startsExpr": false,
        "rightAssociative": false,
        "isLoop": false,
        "isAssign": false,
        "prefix": false,
        "postfix": false,
        "binop": null,
        "updateContext": null
      },
      "start": 608,
      "end": 609,
      "loc": {
        "start": {
          "line": 23,
          "column": 33
        },
        "end": {
          "line": 23,
          "column": 34
        }
      }
    },
    {
      "type": {
        "label": "name",
        "beforeExpr": false,
        "startsExpr": true,
        "rightAssociative": false,
        "isLoop": false,
        "isAssign": false,
        "prefix": false,
        "postfix": false,
        "binop": null
      },
      "value": "c",
      "start": 610,
      "end": 611,
      "loc": {
        "start": {
          "line": 23,
          "column": 35
        },
        "end": {
          "line": 23,
          "column": 36
        }
      }
    },
    {
      "type": {
        "label": ")",
        "beforeExpr": false,
        "startsExpr": false,
        "rightAssociative": false,
        "isLoop": false,
        "isAssign": false,
        "prefix": false,
        "postfix": false,
        "binop": null
      },
      "start": 611,
      "end": 612,
      "loc": {
        "start": {
          "line": 23,
          "column": 36
        },
        "end": {
          "line": 23,
          "column": 37
        }
      }
    },
    {
      "type": {
        "label": ";",
        "beforeExpr": true,
        "startsExpr": false,
        "rightAssociative": false,
        "isLoop": false,
        "isAssign": false,
        "prefix": false,
        "postfix": false,
        "binop": null,
        "updateContext": null
      },
      "start": 612,
      "end": 613,
      "loc": {
        "start": {
          "line": 23,
          "column": 37
        },
        "end": {
          "line": 23,
          "column": 38
        }
      }
    },
    {
      "type": {
        "label": "}",
        "beforeExpr": false,
        "startsExpr": false,
        "rightAssociative": false,
        "isLoop": false,
        "isAssign": false,
        "prefix": false,
        "postfix": false,
        "binop": null
      },
      "start": 616,
      "end": 617,
      "loc": {
        "start": {
          "line": 24,
          "column": 2
        },
        "end": {
          "line": 24,
          "column": 3
        }
      }
    },
    {
      "type": {
        "label": "name",
        "beforeExpr": false,
        "startsExpr": true,
        "rightAssociative": false,
        "isLoop": false,
        "isAssign": false,
        "prefix": false,
        "postfix": false,
        "binop": null
      },
      "value": "initialize",
      "start": 621,
      "end": 631,
      "loc": {
        "start": {
          "line": 26,
          "column": 2
        },
        "end": {
          "line": 26,
          "column": 12
        }
      }
    },
    {
      "type": {
        "label": "(",
        "beforeExpr": true,
        "startsExpr": true,
        "rightAssociative": false,
        "isLoop": false,
        "isAssign": false,
        "prefix": false,
        "postfix": false,
        "binop": null
      },
      "start": 631,
      "end": 632,
      "loc": {
        "start": {
          "line": 26,
          "column": 12
        },
        "end": {
          "line": 26,
          "column": 13
        }
      }
    },
    {
      "type": {
        "label": "name",
        "beforeExpr": false,
        "startsExpr": true,
        "rightAssociative": false,
        "isLoop": false,
        "isAssign": false,
        "prefix": false,
        "postfix": false,
        "binop": null
      },
      "value": "particle",
      "start": 632,
      "end": 640,
      "loc": {
        "start": {
          "line": 26,
          "column": 13
        },
        "end": {
          "line": 26,
          "column": 21
        }
      }
    },
    {
      "type": {
        "label": ")",
        "beforeExpr": false,
        "startsExpr": false,
        "rightAssociative": false,
        "isLoop": false,
        "isAssign": false,
        "prefix": false,
        "postfix": false,
        "binop": null
      },
      "start": 640,
      "end": 641,
      "loc": {
        "start": {
          "line": 26,
          "column": 21
        },
        "end": {
          "line": 26,
          "column": 22
        }
      }
    },
    {
      "type": {
        "label": "{",
        "beforeExpr": true,
        "startsExpr": true,
        "rightAssociative": false,
        "isLoop": false,
        "isAssign": false,
        "prefix": false,
        "postfix": false,
        "binop": null
      },
      "start": 642,
      "end": 643,
      "loc": {
        "start": {
          "line": 26,
          "column": 23
        },
        "end": {
          "line": 26,
          "column": 24
        }
      }
    },
    {
      "type": {
        "label": "name",
        "beforeExpr": false,
        "startsExpr": true,
        "rightAssociative": false,
        "isLoop": false,
        "isAssign": false,
        "prefix": false,
        "postfix": false,
        "binop": null
      },
      "value": "particle",
      "start": 648,
      "end": 656,
      "loc": {
        "start": {
          "line": 27,
          "column": 4
        },
        "end": {
          "line": 27,
          "column": 12
        }
      }
    },
    {
      "type": {
        "label": ".",
        "beforeExpr": false,
        "startsExpr": false,
        "rightAssociative": false,
        "isLoop": false,
        "isAssign": false,
        "prefix": false,
        "postfix": false,
        "binop": null,
        "updateContext": null
      },
      "start": 656,
      "end": 657,
      "loc": {
        "start": {
          "line": 27,
          "column": 12
        },
        "end": {
          "line": 27,
          "column": 13
        }
      }
    },
    {
      "type": {
        "label": "name",
        "beforeExpr": false,
        "startsExpr": true,
        "rightAssociative": false,
        "isLoop": false,
        "isAssign": false,
        "prefix": false,
        "postfix": false,
        "binop": null
      },
      "value": "radius",
      "start": 657,
      "end": 663,
      "loc": {
        "start": {
          "line": 27,
          "column": 13
        },
        "end": {
          "line": 27,
          "column": 19
        }
      }
    },
    {
      "type": {
        "label": "=",
        "beforeExpr": true,
        "startsExpr": false,
        "rightAssociative": false,
        "isLoop": false,
        "isAssign": true,
        "prefix": false,
        "postfix": false,
        "binop": null,
        "updateContext": null
      },
      "value": "=",
      "start": 664,
      "end": 665,
      "loc": {
        "start": {
          "line": 27,
          "column": 20
        },
        "end": {
          "line": 27,
          "column": 21
        }
      }
    },
    {
      "type": {
        "label": "this",
        "keyword": "this",
        "beforeExpr": false,
        "startsExpr": true,
        "rightAssociative": false,
        "isLoop": false,
        "isAssign": false,
        "prefix": false,
        "postfix": false,
        "binop": null,
        "updateContext": null
      },
      "value": "this",
      "start": 666,
      "end": 670,
      "loc": {
        "start": {
          "line": 27,
          "column": 22
        },
        "end": {
          "line": 27,
          "column": 26
        }
      }
    },
    {
      "type": {
        "label": ".",
        "beforeExpr": false,
        "startsExpr": false,
        "rightAssociative": false,
        "isLoop": false,
        "isAssign": false,
        "prefix": false,
        "postfix": false,
        "binop": null,
        "updateContext": null
      },
      "start": 670,
      "end": 671,
      "loc": {
        "start": {
          "line": 27,
          "column": 26
        },
        "end": {
          "line": 27,
          "column": 27
        }
      }
    },
    {
      "type": {
        "label": "name",
        "beforeExpr": false,
        "startsExpr": true,
        "rightAssociative": false,
        "isLoop": false,
        "isAssign": false,
        "prefix": false,
        "postfix": false,
        "binop": null
      },
      "value": "radius",
      "start": 671,
      "end": 677,
      "loc": {
        "start": {
          "line": 27,
          "column": 27
        },
        "end": {
          "line": 27,
          "column": 33
        }
      }
    },
    {
      "type": {
        "label": ".",
        "beforeExpr": false,
        "startsExpr": false,
        "rightAssociative": false,
        "isLoop": false,
        "isAssign": false,
        "prefix": false,
        "postfix": false,
        "binop": null,
        "updateContext": null
      },
      "start": 677,
      "end": 678,
      "loc": {
        "start": {
          "line": 27,
          "column": 33
        },
        "end": {
          "line": 27,
          "column": 34
        }
      }
    },
    {
      "type": {
        "label": "name",
        "beforeExpr": false,
        "startsExpr": true,
        "rightAssociative": false,
        "isLoop": false,
        "isAssign": false,
        "prefix": false,
        "postfix": false,
        "binop": null
      },
      "value": "getValue",
      "start": 678,
      "end": 686,
      "loc": {
        "start": {
          "line": 27,
          "column": 34
        },
        "end": {
          "line": 27,
          "column": 42
        }
      }
    },
    {
      "type": {
        "label": "(",
        "beforeExpr": true,
        "startsExpr": true,
        "rightAssociative": false,
        "isLoop": false,
        "isAssign": false,
        "prefix": false,
        "postfix": false,
        "binop": null
      },
      "start": 686,
      "end": 687,
      "loc": {
        "start": {
          "line": 27,
          "column": 42
        },
        "end": {
          "line": 27,
          "column": 43
        }
      }
    },
    {
      "type": {
        "label": ")",
        "beforeExpr": false,
        "startsExpr": false,
        "rightAssociative": false,
        "isLoop": false,
        "isAssign": false,
        "prefix": false,
        "postfix": false,
        "binop": null
      },
      "start": 687,
      "end": 688,
      "loc": {
        "start": {
          "line": 27,
          "column": 43
        },
        "end": {
          "line": 27,
          "column": 44
        }
      }
    },
    {
      "type": {
        "label": ";",
        "beforeExpr": true,
        "startsExpr": false,
        "rightAssociative": false,
        "isLoop": false,
        "isAssign": false,
        "prefix": false,
        "postfix": false,
        "binop": null,
        "updateContext": null
      },
      "start": 688,
      "end": 689,
      "loc": {
        "start": {
          "line": 27,
          "column": 44
        },
        "end": {
          "line": 27,
          "column": 45
        }
      }
    },
    {
      "type": {
        "label": "name",
        "beforeExpr": false,
        "startsExpr": true,
        "rightAssociative": false,
        "isLoop": false,
        "isAssign": false,
        "prefix": false,
        "postfix": false,
        "binop": null
      },
      "value": "particle",
      "start": 694,
      "end": 702,
      "loc": {
        "start": {
          "line": 28,
          "column": 4
        },
        "end": {
          "line": 28,
          "column": 12
        }
      }
    },
    {
      "type": {
        "label": ".",
        "beforeExpr": false,
        "startsExpr": false,
        "rightAssociative": false,
        "isLoop": false,
        "isAssign": false,
        "prefix": false,
        "postfix": false,
        "binop": null,
        "updateContext": null
      },
      "start": 702,
      "end": 703,
      "loc": {
        "start": {
          "line": 28,
          "column": 12
        },
        "end": {
          "line": 28,
          "column": 13
        }
      }
    },
    {
      "type": {
        "label": "name",
        "beforeExpr": false,
        "startsExpr": true,
        "rightAssociative": false,
        "isLoop": false,
        "isAssign": false,
        "prefix": false,
        "postfix": false,
        "binop": null
      },
      "value": "transform",
      "start": 703,
      "end": 712,
      "loc": {
        "start": {
          "line": 28,
          "column": 13
        },
        "end": {
          "line": 28,
          "column": 22
        }
      }
    },
    {
      "type": {
        "label": ".",
        "beforeExpr": false,
        "startsExpr": false,
        "rightAssociative": false,
        "isLoop": false,
        "isAssign": false,
        "prefix": false,
        "postfix": false,
        "binop": null,
        "updateContext": null
      },
      "start": 712,
      "end": 713,
      "loc": {
        "start": {
          "line": 28,
          "column": 22
        },
        "end": {
          "line": 28,
          "column": 23
        }
      }
    },
    {
      "type": {
        "label": "name",
        "beforeExpr": false,
        "startsExpr": true,
        "rightAssociative": false,
        "isLoop": false,
        "isAssign": false,
        "prefix": false,
        "postfix": false,
        "binop": null
      },
      "value": "oldRadius",
      "start": 713,
      "end": 722,
      "loc": {
        "start": {
          "line": 28,
          "column": 23
        },
        "end": {
          "line": 28,
          "column": 32
        }
      }
    },
    {
      "type": {
        "label": "=",
        "beforeExpr": true,
        "startsExpr": false,
        "rightAssociative": false,
        "isLoop": false,
        "isAssign": true,
        "prefix": false,
        "postfix": false,
        "binop": null,
        "updateContext": null
      },
      "value": "=",
      "start": 723,
      "end": 724,
      "loc": {
        "start": {
          "line": 28,
          "column": 33
        },
        "end": {
          "line": 28,
          "column": 34
        }
      }
    },
    {
      "type": {
        "label": "name",
        "beforeExpr": false,
        "startsExpr": true,
        "rightAssociative": false,
        "isLoop": false,
        "isAssign": false,
        "prefix": false,
        "postfix": false,
        "binop": null
      },
      "value": "particle",
      "start": 725,
      "end": 733,
      "loc": {
        "start": {
          "line": 28,
          "column": 35
        },
        "end": {
          "line": 28,
          "column": 43
        }
      }
    },
    {
      "type": {
        "label": ".",
        "beforeExpr": false,
        "startsExpr": false,
        "rightAssociative": false,
        "isLoop": false,
        "isAssign": false,
        "prefix": false,
        "postfix": false,
        "binop": null,
        "updateContext": null
      },
      "start": 733,
      "end": 734,
      "loc": {
        "start": {
          "line": 28,
          "column": 43
        },
        "end": {
          "line": 28,
          "column": 44
        }
      }
    },
    {
      "type": {
        "label": "name",
        "beforeExpr": false,
        "startsExpr": true,
        "rightAssociative": false,
        "isLoop": false,
        "isAssign": false,
        "prefix": false,
        "postfix": false,
        "binop": null
      },
      "value": "radius",
      "start": 734,
      "end": 740,
      "loc": {
        "start": {
          "line": 28,
          "column": 44
        },
        "end": {
          "line": 28,
          "column": 50
        }
      }
    },
    {
      "type": {
        "label": ";",
        "beforeExpr": true,
        "startsExpr": false,
        "rightAssociative": false,
        "isLoop": false,
        "isAssign": false,
        "prefix": false,
        "postfix": false,
        "binop": null,
        "updateContext": null
      },
      "start": 740,
      "end": 741,
      "loc": {
        "start": {
          "line": 28,
          "column": 50
        },
        "end": {
          "line": 28,
          "column": 51
        }
      }
    },
    {
      "type": {
        "label": "}",
        "beforeExpr": false,
        "startsExpr": false,
        "rightAssociative": false,
        "isLoop": false,
        "isAssign": false,
        "prefix": false,
        "postfix": false,
        "binop": null
      },
      "start": 744,
      "end": 745,
      "loc": {
        "start": {
          "line": 29,
          "column": 2
        },
        "end": {
          "line": 29,
          "column": 3
        }
      }
    },
    {
      "type": {
        "label": "}",
        "beforeExpr": false,
        "startsExpr": false,
        "rightAssociative": false,
        "isLoop": false,
        "isAssign": false,
        "prefix": false,
        "postfix": false,
        "binop": null
      },
      "start": 746,
      "end": 747,
      "loc": {
        "start": {
          "line": 30,
          "column": 0
        },
        "end": {
          "line": 30,
          "column": 1
        }
      }
    },
    {
      "type": {
        "label": "eof",
        "beforeExpr": false,
        "startsExpr": false,
        "rightAssociative": false,
        "isLoop": false,
        "isAssign": false,
        "prefix": false,
        "postfix": false,
        "binop": null,
        "updateContext": null
      },
      "start": 748,
      "end": 748,
      "loc": {
        "start": {
          "line": 31,
          "column": 0
        },
        "end": {
          "line": 31,
          "column": 0
        }
      }
    }
  ]
}