{
  "masterPicture": "public/favicon/nebula-logo-favicon-master.svg",
  "iconsPath": "/",
  "design": {
    "ios": {
      "pictureAspect": "backgroundAndMargin",
      "backgroundColor": "#000000",
      "margin": "35%",
      "assets": {
        "ios6AndPriorIcons": false,
        "ios7AndLaterIcons": false,
        "precomposedIcons": false,
        "declareOnlyDefaultIcon": true
      }
    },
    "desktopBrowser": {},
    "windows": {
      "pictureAspect": "noChange",
      "backgroundColor": "#000000",
      "onConflict": "override",
      "assets": {
        "windows80Ie10Tile": false,
        "windows10Ie11EdgeTiles": {
          "small": false,
          "medium": true,
          "big": false,
          "rectangle": false
        }
      }
    },
    "androidChrome": {
      "pictureAspect": "backgroundAndMargin",
      "margin": "21%",
      "backgroundColor": "#000000",
      "themeColor": "#000000",
      "manifest": {
        "name": "nebula",
        "display": "standalone",
        "orientation": "notSet",
        "onConflict": "override",
        "declared": true
      },
      "assets": {
        "legacyIcon": false,
        "lowResolutionIcons": false
      }
    },
    "safariPinnedTab": {
      "pictureAspect": "silhouette",
      "themeColor": "#4325fb"
    }
  },
  "settings": {
    "compression": 2,
    "scalingAlgorithm": "Mitchell",
    "errorOnImageTooSmall": false,
    "readmeFile": false,
    "htmlCodeFile": false,
    "usePathAsIs": false
  }
}
